{
  "favorites": [
    "ssh-manager.py",
    "compress-images.py",
    "copy-changed-files.py",
    "video-converter.py"
  ],
  "recent": [
    "ssh-manager.py",
    "copy-changed-files.py",
    "generate-tree.py",
    "git-push-source.py",
    "compress-images.py",
    "qr-code.py",
    "scan-malware.py",
    "json-formatter.py",
    "video-converter.py",
    "setup-project-linux.py"
  ],
  "settings": {
    "show_descriptions": false,
    "max_recent": 10
  },
  "disabled_tools": [
    "bootstrap.py",
    "optimize-image.py",
    "search-replace.py",
    "setup-project-linux.py",
    "optimize-shrinkpdf.py",
    "docker-setup-laravel.py",
    "docker-setup.py",
    "wordpress_auto_install.py"
  ],
  "statistics": {
    "tool_usage": {
      "ssh-manager.py": 5,
      "copy-changed-files.py": 6
    },
    "last_used": {
      "ssh-manager.py": 1766470166.4072776,
      "copy-changed-files.py": 1765265905.9708328
    }
  }
}